hun_date_parser/__init__.py
hun_date_parser/date_parser/__init__.py
hun_date_parser/date_parser/date_parsers.py
hun_date_parser/date_parser/datetime_extractor.py
hun_date_parser/date_parser/patterns.py
hun_date_parser/date_parser/structure_parsers.py
hun_date_parser/date_parser/time_parsers.py
hun_date_parser/date_parser/interval_restriction/__init__.py
hun_date_parser/date_parser/interval_restriction/restricted_parsing.py
hun_date_parser/date_textualizer/__init__.py
hun_date_parser/date_textualizer/date2text.py
hun_date_parser/date_textualizer/datetime_textualizer.py
hun_date_parser/date_textualizer/time2text.py
hun_date_parser/duration_parser/__init__.py
hun_date_parser/duration_parser/duration_parsers.py
hun_date_parser/frequency_parser/__init__.py
hun_date_parser/frequency_parser/frequency_parsers.py
hun_date_parser/utils/__init__.py
hun_date_parser/utils/duration_utils.py
hun_date_parser/utils/general_utils.py
test/__init__.py
test/test_date_parsers.py
test/test_date_with_spans.py
test/test_datetime2text.py
test/test_datetime_extractor.py
test/test_datetime_extractor_spans.py
test/test_day_of_month.py
test/test_duration_parser.py
test/test_exposed.py
test/test_frequency_parser.py
test/test_restricted_parsing.py
test/test_spans.py
test/test_structure_parsers.py
test/test_time_parsers.py
test/test_utils.py
hun_date_parser-0.3.2.dist-info/METADATA
hun_date_parser-0.3.2.dist-info/WHEEL
hun_date_parser-0.3.2.dist-info/top_level.txt
hun_date_parser-0.3.2.dist-info/RECORD
