Metadata-Version: 2.4
Name: hun-date-parser
Version: 0.3.2
Summary: A tool for extracting datetime intervals from Hungarian sentences and turning datetime objects into Hungarian text.
Home-page: https://github.com/szegedai/hun-date-parser
Author: Soma Nagy
Author-email: nagysomabalint@gmail.com
Classifier: Programming Language :: Python :: 3
Classifier: License :: OSI Approved :: MIT License
Classifier: Operating System :: OS Independent
Requires-Python: >=3.6
Requires-Dist: python-dateutil
Dynamic: author
Dynamic: author-email
Dynamic: classifier
Dynamic: description
Dynamic: description-content-type
Dynamic: home-page
Dynamic: requires-dist
Dynamic: requires-python
Dynamic: summary
